LICENSE
MANIFEST.in
README.rst
setup.py
json2rust/__init__.py
json2rust/converter.py
json2rust.egg-info/PKG-INFO
json2rust.egg-info/SOURCES.txt
json2rust.egg-info/dependency_links.txt
json2rust.egg-info/entry_points.txt
json2rust.egg-info/top_level.txt
json2rust/.ropeproject/config.py